rtl/decode/decoder.sv
module decoder (
    input  logic [31:0] instruction,

    output logic [6:0] opcode,
    output logic [4:0] rd,
    output logic [2:0] funct3,
    output logic [4:0] rs1,
    output logic [4:0] rs2,
    output logic [6:0] funct7
);

    assign opcode = instruction[6:0];
    assign rd     = instruction[11:7];
    assign funct3 = instruction[14:12];
    assign rs1    = instruction[19:15];
    assign rs2    = instruction[24:20];
    assign funct7 = instruction[31:25];

endmodule

tb/block_tests/decode/decoder_tb.sv
module decoder_tb;

    logic [31:0] instruction;

    logic [6:0] opcode;
    logic [4:0] rd;
    logic [2:0] funct3;
    logic [4:0] rs1;
    logic [4:0] rs2;
    logic [6:0] funct7;

    logic [6:0] expected_opcode;
    logic [4:0] expected_rd;
    logic [2:0] expected_funct3;
    logic [4:0] expected_rs1;
    logic [4:0] expected_rs2;
    logic [6:0] expected_funct7;

    int errors;

    // DUT
    decoder dut (
        .instruction(instruction),
        .opcode(opcode),
        .rd(rd),
        .funct3(funct3),
        .rs1(rs1),
        .rs2(rs2),
        .funct7(funct7)
    );

    initial begin

        $dumpfile("sim/block_sim/decode/decoder.vcd");
        $dumpvars(0, decoder_tb);

        errors = 0;

        // directed tests (sanity)
        instruction = 32'h00000000; #1;
        check();

        instruction = 32'hFFFFFFFF; #1;
        check();

        // random tests
        repeat (100) begin
            instruction = $urandom;
            #1;
            check();
        end

        if (errors == 0)
            $display("PASS");
        else
            $display("FAIL: %0d errors", errors);

        $finish;
    end

    task check;
        begin
            // expected values
            expected_opcode = instruction[6:0];
            expected_rd     = instruction[11:7];
            expected_funct3 = instruction[14:12];
            expected_rs1    = instruction[19:15];
            expected_rs2    = instruction[24:20];
            expected_funct7 = instruction[31:25];

            if (opcode !== expected_opcode ||
                rd     !== expected_rd     ||
                funct3 !== expected_funct3 ||
                rs1    !== expected_rs1    ||
                rs2    !== expected_rs2    ||
                funct7 !== expected_funct7) begin

                $display("ERROR:");
                $display("instr=%h", instruction);
                $display("opcode=%h exp=%h", opcode, expected_opcode);
                $display("rd=%h exp=%h", rd, expected_rd);
                $display("funct3=%h exp=%h", funct3, expected_funct3);
                $display("rs1=%h exp=%h", rs1, expected_rs1);
                $display("rs2=%h exp=%h", rs2, expected_rs2);
                $display("funct7=%h exp=%h", funct7, expected_funct7);

                errors++;
            end
        end
    endtask

endmodule

sim/block_sim/decode/decoder.vcd
$version Generated by VerilatedVcd $end
$timescale 1ps $end
 $scope module TOP $end
  $scope module decoder_tb $end
   $var wire 32 # instruction [31:0] $end
   $var wire 7 $ opcode [6:0] $end
   $var wire 5 % rd [4:0] $end
   $var wire 3 & funct3 [2:0] $end
   $var wire 5 ' rs1 [4:0] $end
   $var wire 5 ( rs2 [4:0] $end
   $var wire 7 ) funct7 [6:0] $end
   $var wire 7 * expected_opcode [6:0] $end
   $var wire 5 + expected_rd [4:0] $end
   $var wire 3 , expected_funct3 [2:0] $end
   $var wire 5 - expected_rs1 [4:0] $end
   $var wire 5 . expected_rs2 [4:0] $end
   $var wire 7 / expected_funct7 [6:0] $end
   $var wire 32 0 errors [31:0] $end
   $scope module dut $end
    $var wire 32 # instruction [31:0] $end
    $var wire 7 $ opcode [6:0] $end
    $var wire 5 % rd [4:0] $end
    $var wire 3 & funct3 [2:0] $end
    $var wire 5 ' rs1 [4:0] $end
    $var wire 5 ( rs2 [4:0] $end
    $var wire 7 ) funct7 [6:0] $end
   $upscope $end
  $upscope $end
 $upscope $end
$enddefinitions $end


#0
b00000000000000000000000000000000 #
b0000000 $
b00000 %
b000 &
b00000 '
b00000 (
b0000000 )
b0000000 *
b00000 +
b000 ,
b00000 -
b00000 .
b0000000 /
b00000000000000000000000000000000 0
#1
b11111111111111111111111111111111 #
b1111111 $
b11111 %
b111 &
b11111 '
b11111 (
b1111111 )
#2
b01111001011101100111001111000100 #
b1000100 $
b00111 %
b01100 '
b10111 (
b0111100 )
b1111111 *
b11111 +
b111 ,
b11111 -
b11111 .
b1111111 /
#3
b00001011000111100101110110011100 #
b0011100 $
b11011 %
b101 &
b11100 '
b10001 (
b0000101 )
b1000100 *
b00111 +
b01100 -
b10111 .
b0111100 /
#4
b10011110111111011101010100000010 #
b0000010 $
b01010 %
b11011 '
b01111 (
b1001111 )
b0011100 *
b11011 +
b101 ,
b11100 -
b10001 .
b0000101 /
#5
b01001000110000101110000011100100 #
b1100100 $
b00001 %
b110 &
b00101 '
b01100 (
b0100100 )
b0000010 *
b01010 +
b11011 -
b01111 .
b1001111 /
#6
b10010010000101111000001101111000 #
b1111000 $
b00110 %
b000 &
b01111 '
b00001 (
b1001001 )
b1100100 *
b00001 +
b110 ,
b00101 -
b01100 .
b0100100 /
#7
b10111011110101011000111010111100 #
b0111100 $
b11101 %
b01011 '
b11101 (
b1011101 )
b1111000 *
b00110 +
b000 ,
b01111 -
b00001 .
b1001001 /
#8
b11001010101001001001111010110110 #
b0110110 $
b001 &
b01001 '
b01010 (
b1100101 )
b0111100 *
b11101 +
b01011 -
b11101 .
b1011101 /
#9
b00101010000101001111111111100100 #
b1100100 $
b11111 %
b111 &
b00001 (
b0010101 )
b0110110 *
b001 ,
b01001 -
b01010 .
b1100101 /
#10
b01111101011011111111001110110111 #
b0110111 $
b00111 %
b11111 '
b10110 (
b0111110 )
b1100100 *
b11111 +
b111 ,
b00001 .
b0010101 /
#11
b11111100110001000111000101010011 #
b1010011 $
b00010 %
b01000 '
b01100 (
b1111110 )
b0110111 *
b00111 +
b11111 -
b10110 .
b0111110 /
#12
b01101111100111100001011100100001 #
b0100001 $
b01110 %
b001 &
b11100 '
b11001 (
b0110111 )
b1010011 *
b00010 +
b01000 -
b01100 .
b1111110 /
#13
b10001010100110100111110111100001 #
b1100001 $
b11011 %
b111 &
b10100 '
b01001 (
b1000101 )
b0100001 *
b01110 +
b001 ,
b11100 -
b11001 .
b0110111 /
#14
b11011111100011001010111111000101 #
b1000101 $
b11111 %
b010 &
b11001 '
b11000 (
b1101111 )
b1100001 *
b11011 +
b111 ,
b10100 -
b01001 .
b1000101 /
#15
b00010010010100111111001110000010 #
b0000010 $
b00111 %
b111 &
b00111 '
b00101 (
b0001001 )
b1000101 *
b11111 +
b010 ,
b11001 -
b11000 .
b1101111 /
#16
b10100100010100011111111101100010 #
b1100010 $
b11110 %
b00011 '
b1010010 )
b0000010 *
b00111 +
b111 ,
b00111 -
b00101 .
b0001001 /
#17
b01110011010110000001011000110101 #
b0110101 $
b01100 %
b001 &
b10000 '
b10101 (
b0111001 )
b1100010 *
b11110 +
b00011 -
b1010010 /
#18
b10101101111110111100100100010010 #
b0010010 $
b10010 %
b100 &
b10111 '
b11111 (
b1010110 )
b0110101 *
b01100 +
b001 ,
b10000 -
b10101 .
b0111001 /
#19
b01100010111110011010101101010110 #
b1010110 $
b10110 %
b010 &
b10011 '
b01111 (
b0110001 )
b0010010 *
b10010 +
b100 ,
b10111 -
b11111 .
b1010110 /
#20
b10110100001100100011101111111101 #
b1111101 $
b10111 %
b011 &
b00100 '
b00011 (
b1011010 )
b1010110 *
b10110 +
b010 ,
b10011 -
b01111 .
b0110001 /
#21
b11011100011010110100000111110100 #
b1110100 $
b00011 %
b100 &
b10110 '
b00110 (
b1101110 )
b1111101 *
b10111 +
b011 ,
b00100 -
b00011 .
b1011010 /
#22
b00000110101011011111010100111011 #
b0111011 $
b01010 %
b111 &
b11011 '
b01010 (
b0000011 )
b1110100 *
b00011 +
b100 ,
b10110 -
b00110 .
b1101110 /
#23
b11000110011011010100110101011000 #
b1011000 $
b11010 %
b100 &
b11010 '
b00110 (
b1100011 )
b0111011 *
b01010 +
b111 ,
b11011 -
b01010 .
b0000011 /
#24
b11101001110011110000010010110010 #
b0110010 $
b01001 %
b000 &
b11110 '
b11100 (
b1110100 )
b1011000 *
b11010 +
b100 ,
b11010 -
b00110 .
b1100011 /
#25
b01010110110100010000100001011100 #
b1011100 $
b10000 %
b00010 '
b01101 (
b0101011 )
b0110010 *
b01001 +
b000 ,
b11110 -
b11100 .
b1110100 /
#26
b01011010000110111000010100011110 #
b0011110 $
b01010 %
b10111 '
b00001 (
b0101101 )
b1011100 *
b10000 +
b00010 -
b01101 .
b0101011 /
#27
b10101101000111110100010110011110 #
b01011 %
b100 &
b11110 '
b10001 (
b1010110 )
b0011110 *
b01010 +
b10111 -
b00001 .
b0101101 /
#28
b00111101111110001001100110011110 #
b10011 %
b001 &
b10001 '
b11111 (
b0011110 )
b01011 +
b100 ,
b11110 -
b10001 .
b1010110 /
#29
b01111011001100110001110011101110 #
b1101110 $
b11001 %
b00110 '
b10011 (
b0111101 )
b10011 +
b001 ,
b10001 -
b11111 .
b0011110 /
#30
b10011000001110110110101100010000 #
b0010000 $
b10110 %
b110 &
b10110 '
b00011 (
b1001100 )
b1101110 *
b11001 +
b00110 -
b10011 .
b0111101 /
#31
b01000000111110110111111101110110 #
b1110110 $
b11110 %
b111 &
b01111 (
b0100000 )
b0010000 *
b10110 +
b110 ,
b10110 -
b00011 .
b1001100 /
#32
b01011010010100001110110101100011 #
b1100011 $
b11010 %
b110 &
b00001 '
b00101 (
b0101101 )
b1110110 *
b11110 +
b111 ,
b01111 .
b0100000 /
#33
b01011001100111111010001011000000 #
b1000000 $
b00101 %
b010 &
b11111 '
b11001 (
b0101100 )
b1100011 *
b11010 +
b110 ,
b00001 -
b00101 .
b0101101 /
#34
b00000001110010001011101100011101 #
b0011101 $
b10110 %
b011 &
b10001 '
b11100 (
b0000000 )
b1000000 *
b00101 +
b010 ,
b11111 -
b11001 .
b0101100 /
#35
b11000001000110110000111100100010 #
b0100010 $
b11110 %
b000 &
b10110 '
b10001 (
b1100000 )
b0011101 *
b10110 +
b011 ,
b10001 -
b11100 .
b0000000 /
#36
b11101111100100111000111100000110 #
b0000110 $
b00111 '
b11001 (
b1110111 )
b0100010 *
b11110 +
b000 ,
b10110 -
b10001 .
b1100000 /
#37
b10000101111011100101101110000001 #
b0000001 $
b10111 %
b101 &
b11100 '
b11110 (
b1000010 )
b0000110 *
b00111 -
b11001 .
b1110111 /
#38
b01111001001011010011001001100011 #
b1100011 $
b00100 %
b011 &
b11010 '
b10010 (
b0111100 )
b0000001 *
b10111 +
b101 ,
b11100 -
b11110 .
b1000010 /
#39
b11000100010101001100001001111000 #
b1111000 $
b100 &
b01001 '
b00101 (
b1100010 )
b1100011 *
b00100 +
b011 ,
b11010 -
b10010 .
b0111100 /
#40
b01100000011000101011111001101111 #
b1101111 $
b11100 %
b011 &
b00101 '
b00110 (
b0110000 )
b1111000 *
b100 ,
b01001 -
b00101 .
b1100010 /
#41
b01100011010101001101101011001110 #
b1001110 $
b10101 %
b101 &
b01001 '
b10101 (
b0110001 )
b1101111 *
b11100 +
b011 ,
b00101 -
b00110 .
b0110000 /
#42
b10010011100000111111111011110111 #
b1110111 $
b11101 %
b111 &
b00111 '
b11000 (
b1001001 )
b1001110 *
b10101 +
b101 ,
b01001 -
b10101 .
b0110001 /
#43
b10010011011110010001101011010001 #
b1010001 $
b10101 %
b001 &
b10010 '
b10111 (
b1110111 *
b11101 +
b111 ,
b00111 -
b11000 .
b1001001 /
#44
b00111100110110011011001110011110 #
b0011110 $
b00111 %
b011 &
b10011 '
b01101 (
b0011110 )
b1010001 *
b10101 +
b001 ,
b10010 -
b10111 .
#45
b10011100010000111101100001110111 #
b1110111 $
b10000 %
b101 &
b00111 '
b00100 (
b1001110 )
b0011110 *
b00111 +
b011 ,
b10011 -
b01101 .
b0011110 /
#46
b11101100010110001100000101101110 #
b1101110 $
b00010 %
b100 &
b10001 '
b00101 (
b1110110 )
b1110111 *
b10000 +
b101 ,
b00111 -
b00100 .
b1001110 /
#47
b11110001101010000000110010101000 #
b0101000 $
b11001 %
b000 &
b10000 '
b11010 (
b1111000 )
b1101110 *
b00010 +
b100 ,
b10001 -
b00101 .
b1110110 /
#48
b10100100101110001110001101001111 #
b1001111 $
b00110 %
b110 &
b10001 '
b01011 (
b1010010 )
b0101000 *
b11001 +
b000 ,
b10000 -
b11010 .
b1111000 /
#49
b01110001111100101001000010111011 #
b0111011 $
b00001 %
b001 &
b00101 '
b11111 (
b0111000 )
b1001111 *
b00110 +
b110 ,
b10001 -
b01011 .
b1010010 /
#50
b00011001101100101000100110010100 #
b0010100 $
b10011 %
b000 &
b11011 (
b0001100 )
b0111011 *
b00001 +
b001 ,
b00101 -
b11111 .
b0111000 /
#51
b10111101000010110010111011100010 #
b1100010 $
b11101 %
b010 &
b10110 '
b10000 (
b1011110 )
b0010100 *
b10011 +
b000 ,
b11011 .
b0001100 /
#52
b10000010011111111111000101100110 #
b1100110 $
b00010 %
b111 &
b11111 '
b00111 (
b1000001 )
b1100010 *
b11101 +
b010 ,
b10110 -
b10000 .
b1011110 /
#53
b11101111111111000001101100011111 #
b0011111 $
b10110 %
b001 &
b11000 '
b11111 (
b1110111 )
b1100110 *
b00010 +
b111 ,
b11111 -
b00111 .
b1000001 /
#54
b10111101010101001011001100001001 #
b0001001 $
b00110 %
b011 &
b01001 '
b10101 (
b1011110 )
b0011111 *
b10110 +
b001 ,
b11000 -
b11111 .
b1110111 /
#55
b11111111100111001011110011100011 #
b1100011 $
b11001 %
b11001 '
b11001 (
b1111111 )
b0001001 *
b00110 +
b011 ,
b01001 -
b10101 .
b1011110 /
#56
b01010111101100001111011000011111 #
b0011111 $
b01100 %
b111 &
b00001 '
b11011 (
b0101011 )
b1100011 *
b11001 +
b11001 -
b11001 .
b1111111 /
#57
b10000001101011011010111110000100 #
b0000100 $
b11111 %
b010 &
b11011 '
b11010 (
b1000000 )
b0011111 *
b01100 +
b111 ,
b00001 -
b11011 .
b0101011 /
#58
b01011111000100000011011011000101 #
b1000101 $
b01101 %
b011 &
b00000 '
b10001 (
b0101111 )
b0000100 *
b11111 +
b010 ,
b11011 -
b11010 .
b1000000 /
#59
b01111001001000011010011000110011 #
b0110011 $
b01100 %
b010 &
b00011 '
b10010 (
b0111100 )
b1000101 *
b01101 +
b011 ,
b00000 -
b10001 .
b0101111 /
#60
b11011111011100101110101001001011 #
b1001011 $
b10100 %
b110 &
b00101 '
b10111 (
b1101111 )
b0110011 *
b01100 +
b010 ,
b00011 -
b10010 .
b0111100 /
#61
b11101110010000100001111010011100 #
b0011100 $
b11101 %
b001 &
b00100 '
b00100 (
b1110111 )
b1001011 *
b10100 +
b110 ,
b00101 -
b10111 .
b1101111 /
#62
b10000110110010001010100011110011 #
b1110011 $
b10001 %
b010 &
b10001 '
b01100 (
b1000011 )
b0011100 *
b11101 +
b001 ,
b00100 -
b00100 .
b1110111 /
#63
b11001110101100110010110011001001 #
b1001001 $
b11001 %
b00110 '
b01011 (
b1100111 )
b1110011 *
b10001 +
b010 ,
b10001 -
b01100 .
b1000011 /
#64
b10010011110111010111111011101101 #
b1101101 $
b11101 %
b111 &
b11010 '
b11101 (
b1001001 )
b1001001 *
b11001 +
b00110 -
b01011 .
b1100111 /
#65
b00011011101110010110010111001010 #
b1001010 $
b01011 %
b110 &
b10010 '
b11011 (
b0001101 )
b1101101 *
b11101 +
b111 ,
b11010 -
b11101 .
b1001001 /
#66
b01111100010010011101010101011101 #
b1011101 $
b01010 %
b101 &
b10011 '
b00100 (
b0111110 )
b1001010 *
b01011 +
b110 ,
b10010 -
b11011 .
b0001101 /
#67
b10101110011000010011010001000111 #
b1000111 $
b01000 %
b011 &
b00010 '
b00110 (
b1010111 )
b1011101 *
b01010 +
b101 ,
b10011 -
b00100 .
b0111110 /
#68
b01000011111001011110110100100100 #
b0100100 $
b11010 %
b110 &
b01011 '
b11110 (
b0100001 )
b1000111 *
b01000 +
b011 ,
b00010 -
b00110 .
b1010111 /
#69
b11000011010010011011001011101111 #
b1101111 $
b00101 %
b011 &
b10011 '
b10100 (
b1100001 )
b0100100 *
b11010 +
b110 ,
b01011 -
b11110 .
b0100001 /
#70
b01011101010101001011010010101001 #
b0101001 $
b01001 %
b01001 '
b10101 (
b0101110 )
b1101111 *
b00101 +
b011 ,
b10011 -
b10100 .
b1100001 /
#71
b11011011111010001101100101101101 #
b1101101 $
b10010 %
b101 &
b10001 '
b11110 (
b1101101 )
b0101001 *
b01001 +
b01001 -
b10101 .
b0101110 /
#72
b01100110000010000011011100111001 #
b0111001 $
b01110 %
b011 &
b10000 '
b00000 (
b0110011 )
b1101101 *
b10010 +
b101 ,
b10001 -
b11110 .
b1101101 /
#73
b01001110111100101001101001111000 #
b1111000 $
b10100 %
b001 &
b00101 '
b01111 (
b0100111 )
b0111001 *
b01110 +
b011 ,
b10000 -
b00000 .
b0110011 /
#74
b00001010100001111110100011101010 #
b1101010 $
b10001 %
b110 &
b01111 '
b01000 (
b0000101 )
b1111000 *
b10100 +
b001 ,
b00101 -
b01111 .
b0100111 /
#75
b01111101111001110011100011000010 #
b1000010 $
b011 &
b01110 '
b11110 (
b0111110 )
b1101010 *
b10001 +
b110 ,
b01111 -
b01000 .
b0000101 /
#76
b11011011011100110000000101010100 #
b1010100 $
b00010 %
b000 &
b00110 '
b10111 (
b1101101 )
b1000010 *
b011 ,
b01110 -
b11110 .
b0111110 /
#77
b00100010101010100100100101010100 #
b10010 %
b100 &
b10100 '
b01010 (
b0010001 )
b1010100 *
b00010 +
b000 ,
b00110 -
b10111 .
b1101101 /
#78
b01101000101000001100101100100011 #
b0100011 $
b10110 %
b00001 '
b0110100 )
b10010 +
b100 ,
b10100 -
b01010 .
b0010001 /
#79
b11101000011000111101000110011101 #
b0011101 $
b00011 %
b101 &
b00111 '
b00110 (
b1110100 )
b0100011 *
b10110 +
b00001 -
b0110100 /
#80
b00100111000010000100001110110011 #
b0110011 $
b00111 %
b100 &
b10000 '
b10000 (
b0010011 )
b0011101 *
b00011 +
b101 ,
b00111 -
b00110 .
b1110100 /
#81
b00111001101111000111111110101101 #
b0101101 $
b11111 %
b111 &
b11000 '
b11011 (
b0011100 )
b0110011 *
b00111 +
b100 ,
b10000 -
b10000 .
b0010011 /
#82
b00110100111010010101000011010101 #
b1010101 $
b00001 %
b101 &
b10010 '
b01110 (
b0011010 )
b0101101 *
b11111 +
b111 ,
b11000 -
b11011 .
b0011100 /
#83
b11001110101110010111101100101110 #
b0101110 $
b10110 %
b111 &
b01011 (
b1100111 )
b1010101 *
b00001 +
b101 ,
b10010 -
b01110 .
b0011010 /
#84
b00001010100001111011100011001111 #
b1001111 $
b10001 %
b011 &
b01111 '
b01000 (
b0000101 )
b0101110 *
b10110 +
b111 ,
b01011 .
b1100111 /
#85
b00011111111111111011001100000101 #
b0000101 $
b00110 %
b11111 '
b11111 (
b0001111 )
b1001111 *
b10001 +
b011 ,
b01111 -
b01000 .
b0000101 /
#86
b00100000101110001001010111010111 #
b1010111 $
b01011 %
b001 &
b10001 '
b01011 (
b0010000 )
b0000101 *
b00110 +
b11111 -
b11111 .
b0001111 /
#87
b00101111110110100000010010001001 #
b0001001 $
b01001 %
b000 &
b10100 '
b11101 (
b0010111 )
b1010111 *
b01011 +
b001 ,
b10001 -
b01011 .
b0010000 /
#88
b11011010110010000100001011110110 #
b1110110 $
b00101 %
b100 &
b10000 '
b01100 (
b1101101 )
b0001001 *
b01001 +
b000 ,
b10100 -
b11101 .
b0010111 /
#89
b10000110010110001001111110101111 #
b0101111 $
b11111 %
b001 &
b10001 '
b00101 (
b1000011 )
b1110110 *
b00101 +
b100 ,
b10000 -
b01100 .
b1101101 /
#90
b10000000111110011111010111101111 #
b1101111 $
b01011 %
b111 &
b10011 '
b01111 (
b1000000 )
b0101111 *
b11111 +
b001 ,
b10001 -
b00101 .
b1000011 /
#91
b01011011111000000010011110011101 #
b0011101 $
b01111 %
b010 &
b00000 '
b11110 (
b0101101 )
b1101111 *
b01011 +
b111 ,
b10011 -
b01111 .
b1000000 /
#92
b10010100111111100100001100111111 #
b0111111 $
b00110 %
b100 &
b11100 '
b01111 (
b1001010 )
b0011101 *
b01111 +
b010 ,
b00000 -
b11110 .
b0101101 /
#93
b11011011000111001100111011001111 #
b1001111 $
b11101 %
b11001 '
b10001 (
b1101101 )
b0111111 *
b00110 +
b100 ,
b11100 -
b01111 .
b1001010 /
#94
b00001111011101011110001100101010 #
b0101010 $
b00110 %
b110 &
b01011 '
b10111 (
b0000111 )
b1001111 *
b11101 +
b11001 -
b10001 .
b1101101 /
#95
b00001001000101001110001101110111 #
b1110111 $
b01001 '
b10001 (
b0000100 )
b0101010 *
b00110 +
b110 ,
b01011 -
b10111 .
b0000111 /
#96
b01001011100101001001101010011010 #
b0011010 $
b10101 %
b001 &
b11001 (
b0100101 )
b1110111 *
b01001 -
b10001 .
b0000100 /
#97
b01011001000001101000011100001011 #
b0001011 $
b01110 %
b000 &
b01101 '
b10000 (
b0101100 )
b0011010 *
b10101 +
b001 ,
b11001 .
b0100101 /
#98
b00100100100011000001111101010011 #
b1010011 $
b11110 %
b001 &
b11000 '
b01000 (
b0010010 )
b0001011 *
b01110 +
b000 ,
b01101 -
b10000 .
b0101100 /
#99
b00011011011110000100001010101111 #
b0101111 $
b00101 %
b100 &
b10000 '
b10111 (
b0001101 )
b1010011 *
b11110 +
b001 ,
b11000 -
b01000 .
b0010010 /
#100
b10001000111100111011100110001100 #
b0001100 $
b10011 %
b011 &
b00111 '
b01111 (
b1000100 )
b0101111 *
b00101 +
b100 ,
b10000 -
b10111 .
b0001101 /
#101
b00010001110110101011001100000010 #
b0000010 $
b00110 %
b10101 '
b11101 (
b0001000 )
b0001100 *
b10011 +
b011 ,
b00111 -
b01111 .
b1000100 /
#102
b0000010 *
b00110 +
b10101 -
b11101 .
b0001000 /
