rtl/utils/mux2.sv
module mux2 #(
    parameter int WIDTH = 32
)(
    input  logic [WIDTH-1:0] a,
    input  logic [WIDTH-1:0] b,
    input  logic sel,
    output logic [WIDTH-1:0] y
);

    always_comb begin
        if (sel)
            y = b;
        else
            y = a;
    end

endmodule

tb/block_tests/utils/mux2_tb.sv
module mux2_tb;

    parameter WIDTH = 32;

    logic clk;
    logic [WIDTH-1:0] a;
    logic [WIDTH-1:0] b;
    logic sel;

    logic [WIDTH-1:0] y;
    logic [WIDTH-1:0] expected;

    int errors = 0;

    // DUT
    mux2 #(.WIDTH(WIDTH)) dut (
        .a(a),
        .b(b),
        .sel(sel),
        .y(y)
    );

    // Clock generator
    always #5 clk <= ~clk;

    initial begin
        clk = 0;

        $dumpfile("sim/block_sim/utils/mux2.vcd");
        $dumpvars(0, mux2_tb);

        repeat (50) begin
            @(posedge clk);

            a   = $urandom;
            b   = $urandom;
            sel = bit'($urandom);

            expected = sel ? b : a;

            #1;

            if (y !== expected) begin
                $display("ERROR: a=%h b=%h sel=%b y=%h expected=%h",
                         a, b, sel, y, expected);
                errors++;
            end
        end

        if (errors == 0)
            $display("PASS: mux2 test successful");
        else
            $display("FAIL: %0d errors detected", errors);

        $finish;
    end

endmodule

sim/block_sim/utils/mux2.vcd
$version Generated by VerilatedVcd $end
$timescale 1ps $end
 $scope module TOP $end
  $scope module mux2_tb $end
   $var wire 32 * WIDTH [31:0] $end
   $var wire 1 ) clk $end
   $var wire 32 # a [31:0] $end
   $var wire 32 $ b [31:0] $end
   $var wire 1 % sel $end
   $var wire 32 & y [31:0] $end
   $var wire 32 ' expected [31:0] $end
   $var wire 32 ( errors [31:0] $end
   $scope module dut $end
    $var wire 32 + WIDTH [31:0] $end
    $var wire 32 # a [31:0] $end
    $var wire 32 $ b [31:0] $end
    $var wire 1 % sel $end
    $var wire 32 & y [31:0] $end
   $upscope $end
  $upscope $end
 $upscope $end
$enddefinitions $end


#0
b00000000000000000000000000000000 #
b00000000000000000000000000000000 $
0%
b00000000000000000000000000000000 &
b00000000000000000000000000000000 '
b00000000000000000000000000000000 (
0)
b00000000000000000000000000100000 *
b00000000000000000000000000100000 +
#5
b01111001011101100111001111000100 #
b00001011000111100101110110011100 $
b01111001011101100111001111000100 &
b01111001011101100111001111000100 '
1)
#6
#10
0)
#15
b01001000110000101110000011100100 #
b10010010000101111000001101111000 $
b01001000110000101110000011100100 &
b01001000110000101110000011100100 '
1)
#16
#20
0)
#25
b11001010101001001001111010110110 #
b00101010000101001111111111100100 $
1%
b00101010000101001111111111100100 &
b00101010000101001111111111100100 '
1)
#26
#30
0)
#35
b11111100110001000111000101010011 #
b01101111100111100001011100100001 $
b01101111100111100001011100100001 &
b01101111100111100001011100100001 '
1)
#36
#40
0)
#45
b11011111100011001010111111000101 #
b00010010010100111111001110000010 $
0%
b11011111100011001010111111000101 &
b11011111100011001010111111000101 '
1)
#46
#50
0)
#55
b01110011010110000001011000110101 #
b10101101111110111100100100010010 $
b01110011010110000001011000110101 &
b01110011010110000001011000110101 '
1)
#56
#60
0)
#65
b10110100001100100011101111111101 #
b11011100011010110100000111110100 $
1%
b11011100011010110100000111110100 &
b11011100011010110100000111110100 '
1)
#66
#70
0)
#75
b11000110011011010100110101011000 #
b11101001110011110000010010110010 $
0%
b11000110011011010100110101011000 &
b11000110011011010100110101011000 '
1)
#76
#80
0)
#85
b01011010000110111000010100011110 #
b10101101000111110100010110011110 $
b01011010000110111000010100011110 &
b01011010000110111000010100011110 '
1)
#86
#90
0)
#95
b01111011001100110001110011101110 #
b10011000001110110110101100010000 $
b01111011001100110001110011101110 &
b01111011001100110001110011101110 '
1)
#96
#100
0)
#105
b01011010010100001110110101100011 #
b01011001100111111010001011000000 $
1%
b01011001100111111010001011000000 &
b01011001100111111010001011000000 '
1)
#106
#110
0)
#115
b11000001000110110000111100100010 #
b11101111100100111000111100000110 $
b11101111100100111000111100000110 &
b11101111100100111000111100000110 '
1)
#116
#120
0)
#125
b01111001001011010011001001100011 #
b11000100010101001100001001111000 $
b11000100010101001100001001111000 &
b11000100010101001100001001111000 '
1)
#126
#130
0)
#135
b01100011010101001101101011001110 #
b10010011100000111111111011110111 $
b10010011100000111111111011110111 &
b10010011100000111111111011110111 '
1)
#136
#140
0)
#145
b00111100110110011011001110011110 #
b10011100010000111101100001110111 $
0%
b00111100110110011011001110011110 &
b00111100110110011011001110011110 '
1)
#146
#150
0)
#155
b11110001101010000000110010101000 #
b10100100101110001110001101001111 $
1%
b10100100101110001110001101001111 &
b10100100101110001110001101001111 '
1)
#156
#160
0)
#165
b00011001101100101000100110010100 #
b10111101000010110010111011100010 $
0%
b00011001101100101000100110010100 &
b00011001101100101000100110010100 '
1)
#166
#170
0)
#175
b11101111111111000001101100011111 #
b10111101010101001011001100001001 $
1%
b10111101010101001011001100001001 &
b10111101010101001011001100001001 '
1)
#176
#180
0)
#185
b01010111101100001111011000011111 #
b10000001101011011010111110000100 $
b10000001101011011010111110000100 &
b10000001101011011010111110000100 '
1)
#186
#190
0)
#195
b01111001001000011010011000110011 #
b11011111011100101110101001001011 $
0%
b01111001001000011010011000110011 &
b01111001001000011010011000110011 '
1)
#196
#200
0)
#205
b10000110110010001010100011110011 #
b11001110101100110010110011001001 $
1%
b11001110101100110010110011001001 &
b11001110101100110010110011001001 '
1)
#206
#210
0)
#215
b00011011101110010110010111001010 #
b01111100010010011101010101011101 $
b01111100010010011101010101011101 &
b01111100010010011101010101011101 '
1)
#216
#220
0)
#225
b01000011111001011110110100100100 #
b11000011010010011011001011101111 $
b11000011010010011011001011101111 &
b11000011010010011011001011101111 '
1)
#226
#230
0)
#235
b11011011111010001101100101101101 #
b01100110000010000011011100111001 $
0%
b11011011111010001101100101101101 &
b11011011111010001101100101101101 '
1)
#236
#240
0)
#245
b00001010100001111110100011101010 #
b01111101111001110011100011000010 $
b00001010100001111110100011101010 &
b00001010100001111110100011101010 '
1)
#246
#250
0)
#255
b00100010101010100100100101010100 #
b01101000101000001100101100100011 $
1%
b01101000101000001100101100100011 &
b01101000101000001100101100100011 '
1)
#256
#260
0)
#265
b00100111000010000100001110110011 #
b00111001101111000111111110101101 $
b00111001101111000111111110101101 &
b00111001101111000111111110101101 '
1)
#266
#270
0)
#275
b11001110101110010111101100101110 #
b00001010100001111011100011001111 $
b00001010100001111011100011001111 &
b00001010100001111011100011001111 '
1)
#276
#280
0)
#285
b00100000101110001001010111010111 #
b00101111110110100000010010001001 $
0%
b00100000101110001001010111010111 &
b00100000101110001001010111010111 '
1)
#286
#290
0)
#295
b10000110010110001001111110101111 #
b10000000111110011111010111101111 $
1%
b10000000111110011111010111101111 &
b10000000111110011111010111101111 '
1)
#296
#300
0)
#305
b10010100111111100100001100111111 #
b11011011000111001100111011001111 $
0%
b10010100111111100100001100111111 &
b10010100111111100100001100111111 '
1)
#306
#310
0)
#315
b00001001000101001110001101110111 #
b01001011100101001001101010011010 $
1%
b01001011100101001001101010011010 &
b01001011100101001001101010011010 '
1)
#316
#320
0)
#325
b00100100100011000001111101010011 #
b00011011011110000100001010101111 $
0%
b00100100100011000001111101010011 &
b00100100100011000001111101010011 '
1)
#326
#330
0)
#335
b00010001110110101011001100000010 #
b11001010100101110010101111111011 $
b00010001110110101011001100000010 &
b00010001110110101011001100000010 '
1)
#336
#340
0)
#345
b10010000000011111101100111000010 #
b01101110011011011100110111011101 $
b10010000000011111101100111000010 &
b10010000000011111101100111000010 '
1)
#346
#350
0)
#355
b10010011011010001101100001100100 #
b00001001011101101010011001100001 $
1%
b00001001011101101010011001100001 &
b00001001011101101010011001100001 '
1)
#356
#360
0)
#365
b00000101111010011101110100100001 #
b10010000110000000010011111110011 $
b10010000110000000010011111110011 &
b10010000110000000010011111110011 '
1)
#366
#370
0)
#375
b00000010011010010001100011110101 #
b10011100000100000001011010111101 $
0%
b00000010011010010001100011110101 &
b00000010011010010001100011110101 '
1)
#376
#380
0)
#385
b01010111101010100010011001100010 #
b01000101011101101001111111001010 $
b01010111101010100010011001100010 &
b01010111101010100010011001100010 '
1)
#386
#390
0)
#395
b00011100100100001100011101000101 #
b01100011011100011110000001011000 $
b00011100100100001100011101000101 &
b00011100100100001100011101000101 '
1)
#396
#400
0)
#405
b11111111110011111101111001100000 #
b10001101101110000000001101110011 $
b11111111110011111101111001100000 &
b11111111110011111101111001100000 '
1)
#406
#410
0)
#415
b00010011010100011100000100111101 #
b10010101110011111010010001101100 $
b00010011010100011100000100111101 &
b00010011010100011100000100111101 '
1)
#416
#420
0)
#425
b01010110010100111001101011100111 #
b01000000001110100101001000110111 $
1%
b01000000001110100101001000110111 &
b01000000001110100101001000110111 '
1)
#426
#430
0)
#435
b00111101110001111001001101000000 #
b01010111000001010100100000110011 $
0%
b00111101110001111001001101000000 &
b00111101110001111001001101000000 '
1)
#436
#440
0)
#445
b11011010110001110001101010110110 #
b11101101110000011110001011010111 $
b11011010110001110001101010110110 &
b11011010110001110001101010110110 '
1)
#446
#450
0)
#455
b10101100000000110100101001100111 #
b01001101010001011111011001010011 $
b10101100000000110100101001100111 &
b10101100000000110100101001100111 '
1)
#456
#460
0)
#465
b00111000011011011110100011110100 #
b01011110111011101000011011100100 $
b00111000011011011110100011110100 &
b00111000011011011110100011110100 '
1)
#466
#470
0)
#475
b11010010111111010100001101100111 #
b10001101001111111101100010010101 $
b11010010111111010100001101100111 &
b11010010111111010100001101100111 '
1)
#476
#480
0)
#485
b11010100101110010001101101100100 #
b11011110110111000100000110010101 $
b11010100101110010001101101100100 &
b11010100101110010001101101100100 '
1)
#486
#490
0)
#495
b10010001101011110100011100111101 #
b00000100110001100111000001111111 $
1%
b00000100110001100111000001111111 &
b00000100110001100111000001111111 '
1)
