rtl/utils/mux3.sv
module mux3 #(
    parameter int WIDTH = 32
    )(
        input logic [WIDTH-1:0] a,
        input logic [WIDTH-1:0] b,
        input logic [WIDTH-1:0] c,
        input logic [1:0] sel,
        output logic [WIDTH-1:0] y
    );
    always_comb begin
        case (sel)
            2'b00: y = a;
            2'b01: y = b;
            2'b10: y = c;
            default: y = a; //handles 2'b11
        endcase
    end
endmodule

tb/block_tests/utils/mux3_tb.sv
module mux3_tb;

    parameter WIDTH = 32;

    logic clk;
    logic [WIDTH-1:0] a;
    logic [WIDTH-1:0] b;
    logic [WIDTH-1:0] c;
    logic [1:0] sel;

    logic [WIDTH-1:0] y;
    logic [WIDTH-1:0] expected;

    int errors = 0;

    //DUT
    mux3 #(.WIDTH(WIDTH)) dut(
        .a(a),
        .b(b),
        .c(c),
        .sel(sel),
        .y(y)
    );

    //clock
    always #5 clk <= ~clk;

    initial begin
        clk = 0;

        $dumpfile("sim/block_sim/utils/mux3.vcd");
        $dumpvars(0, mux3_tb);

        repeat(50) begin
            
            @(posedge clk);

            a = $urandom;
            b = $urandom;
            c = $urandom;
            sel[0] = bit'($urandom);
            sel[1] = bit'($urandom);

            case (sel)
                2'b00: expected = a;
                2'b01: expected = b;
                2'b10: expected = c;
                default: expected = a; //handles 2'b11
            endcase

            #1;

            if (y !== expected) begin
                $display("ERROR: a = %h b = %h c = %h sel = %b y = %h expected = %h",
                        a, b, c, sel, y, expected);
                    errors++;
            end
        end


        if (errors == 0) 
            $display("PASS: mux3 test successful");
        else 
            $display("FAIL: errors detected: %0d",errors);
           
        $finish;
    end

endmodule

sim/block_sim/utils/mux3.vcd
$version Generated by VerilatedVcd $end
$timescale 1ps $end
 $scope module TOP $end
  $scope module mux3_tb $end
   $var wire 32 + WIDTH [31:0] $end
   $var wire 1 * clk $end
   $var wire 32 # a [31:0] $end
   $var wire 32 $ b [31:0] $end
   $var wire 32 % c [31:0] $end
   $var wire 2 & sel [1:0] $end
   $var wire 32 ' y [31:0] $end
   $var wire 32 ( expected [31:0] $end
   $var wire 32 ) errors [31:0] $end
   $scope module dut $end
    $var wire 32 , WIDTH [31:0] $end
    $var wire 32 # a [31:0] $end
    $var wire 32 $ b [31:0] $end
    $var wire 32 % c [31:0] $end
    $var wire 2 & sel [1:0] $end
    $var wire 32 ' y [31:0] $end
   $upscope $end
  $upscope $end
 $upscope $end
$enddefinitions $end


#0
b00000000000000000000000000000000 #
b00000000000000000000000000000000 $
b00000000000000000000000000000000 %
b00 &
b00000000000000000000000000000000 '
b00000000000000000000000000000000 (
b00000000000000000000000000000000 )
0*
b00000000000000000000000000100000 +
b00000000000000000000000000100000 ,
#5
b01111001011101100111001111000100 #
b00001011000111100101110110011100 $
b10011110111111011101010100000010 %
b01111001011101100111001111000100 '
b01111001011101100111001111000100 (
1*
#6
#10
0*
#15
b10010010000101111000001101111000 #
b10111011110101011000111010111100 $
b11001010101001001001111010110110 %
b10010010000101111000001101111000 '
b10010010000101111000001101111000 (
1*
#16
#20
0*
#25
b01111101011011111111001110110111 #
b11111100110001000111000101010011 $
b01101111100111100001011100100001 %
b01 &
b11111100110001000111000101010011 '
b11111100110001000111000101010011 (
1*
#26
#30
0*
#35
b11011111100011001010111111000101 #
b00010010010100111111001110000010 $
b10100100010100011111111101100010 %
b00010010010100111111001110000010 '
b00010010010100111111001110000010 (
1*
#36
#40
0*
#45
b10101101111110111100100100010010 #
b01100010111110011010101101010110 $
b10110100001100100011101111111101 %
b00 &
b10101101111110111100100100010010 '
b10101101111110111100100100010010 (
1*
#46
#50
0*
#55
b00000110101011011111010100111011 #
b11000110011011010100110101011000 $
b11101001110011110000010010110010 %
b00000110101011011111010100111011 '
b00000110101011011111010100111011 (
1*
#56
#60
0*
#65
b01011010000110111000010100011110 #
b10101101000111110100010110011110 $
b00111101111110001001100110011110 %
b10 &
b00111101111110001001100110011110 '
b00111101111110001001100110011110 (
1*
#66
#70
0*
#75
b10011000001110110110101100010000 #
b01000000111110110111111101110110 $
b01011010010100001110110101100011 %
b00 &
b10011000001110110110101100010000 '
b10011000001110110110101100010000 (
1*
#76
#80
0*
#85
b00000001110010001011101100011101 #
b11000001000110110000111100100010 $
b11101111100100111000111100000110 %
b01 &
b11000001000110110000111100100010 '
b11000001000110110000111100100010 (
1*
#86
#90
0*
#95
b01111001001011010011001001100011 #
b11000100010101001100001001111000 $
b01100000011000101011111001101111 %
b10 &
b01100000011000101011111001101111 '
b01100000011000101011111001101111 (
1*
#96
#100
0*
#105
b10010011100000111111111011110111 #
b10010011011110010001101011010001 $
b00111100110110011011001110011110 %
b11 &
b10010011100000111111111011110111 '
b10010011100000111111111011110111 (
1*
#106
#110
0*
#115
b11101100010110001100000101101110 #
b11110001101010000000110010101000 $
b10100100101110001110001101001111 %
b11101100010110001100000101101110 '
b11101100010110001100000101101110 (
1*
#116
#120
0*
#125
b00011001101100101000100110010100 #
b10111101000010110010111011100010 $
b10000010011111111111000101100110 %
b00011001101100101000100110010100 '
b00011001101100101000100110010100 (
1*
#126
#130
0*
#135
b10111101010101001011001100001001 #
b11111111100111001011110011100011 $
b01010111101100001111011000011111 %
b00 &
b10111101010101001011001100001001 '
b10111101010101001011001100001001 (
1*
#136
#140
0*
#145
b01011111000100000011011011000101 #
b01111001001000011010011000110011 $
b11011111011100101110101001001011 %
b01011111000100000011011011000101 '
b01011111000100000011011011000101 (
1*
#146
#150
0*
#155
b10000110110010001010100011110011 #
b11001110101100110010110011001001 $
b10010011110111010111111011101101 %
b10 &
b10010011110111010111111011101101 '
b10010011110111010111111011101101 (
1*
#156
#160
0*
#165
b01111100010010011101010101011101 #
b10101110011000010011010001000111 $
b01000011111001011110110100100100 %
b11 &
b01111100010010011101010101011101 '
b01111100010010011101010101011101 (
1*
#166
#170
0*
#175
b01011101010101001011010010101001 #
b11011011111010001101100101101101 $
b01100110000010000011011100111001 %
b00 &
b01011101010101001011010010101001 '
b01011101010101001011010010101001 (
1*
#176
#180
0*
#185
b00001010100001111110100011101010 #
b01111101111001110011100011000010 $
b11011011011100110000000101010100 %
b00001010100001111110100011101010 '
b00001010100001111110100011101010 (
1*
#186
#190
0*
#195
b01101000101000001100101100100011 #
b11101000011000111101000110011101 $
b00100111000010000100001110110011 %
b01 &
b11101000011000111101000110011101 '
b11101000011000111101000110011101 (
1*
#196
#200
0*
#205
b00110100111010010101000011010101 #
b11001110101110010111101100101110 $
b00001010100001111011100011001111 %
b11001110101110010111101100101110 '
b11001110101110010111101100101110 (
1*
#206
#210
0*
#215
b00100000101110001001010111010111 #
b00101111110110100000010010001001 $
b11011010110010000100001011110110 %
b11 &
b00100000101110001001010111010111 '
b00100000101110001001010111010111 (
1*
#216
#220
0*
#225
b10000000111110011111010111101111 #
b01011011111000000010011110011101 $
b10010100111111100100001100111111 %
b10000000111110011111010111101111 '
b10000000111110011111010111101111 (
1*
#226
#230
0*
#235
b00001111011101011110001100101010 #
b00001001000101001110001101110111 $
b01001011100101001001101010011010 %
b00001111011101011110001100101010 '
b00001111011101011110001100101010 (
1*
#236
#240
0*
#245
b00100100100011000001111101010011 #
b00011011011110000100001010101111 $
b10001000111100111011100110001100 %
b10 &
b10001000111100111011100110001100 '
b10001000111100111011100110001100 (
1*
#246
#250
0*
#255
b11001010100101110010101111111011 #
b10011111001000000001010111101000 $
b10010000000011111101100111000010 %
b01 &
b10011111001000000001010111101000 '
b10011111001000000001010111101000 (
1*
#256
#260
0*
#265
b01000011011010000100000111001000 #
b10010011011010001101100001100100 $
b00001001011101101010011001100001 %
b10010011011010001101100001100100 '
b10010011011010001101100001100100 (
1*
#266
#270
0*
#275
b00000101111010011101110100100001 #
b10010000110000000010011111110011 $
b01101101011100010000010001011001 %
b10010000110000000010011111110011 '
b10010000110000000010011111110011 (
1*
#276
#280
0*
#285
b10011100000100000001011010111101 #
b01000000101101000001101101111110 $
b01010111101010100010011001100010 %
b10 &
b01010111101010100010011001100010 '
b01010111101010100010011001100010 (
1*
#286
#290
0*
#295
b00000111101110100001111010010000 #
b00011100100100001100011101000101 $
b01100011011100011110000001011000 %
b00 &
b00000111101110100001111010010000 '
b00000111101110100001111010010000 (
1*
#296
#300
0*
#305
b11111111110011111101111001100000 #
b10001101101110000000001101110011 $
b10010011011011111000110011111100 %
b01 &
b10001101101110000000001101110011 '
b10001101101110000000001101110011 (
1*
#306
#310
0*
#315
b10010101110011111010010001101100 #
b01000000110011010101001100001110 $
b01010110010100111001101011100111 %
b11 &
b10010101110011111010010001101100 '
b10010101110011111010010001101100 (
1*
#316
#320
0*
#325
b00011000111001111010111001000111 #
b00111101110001111001001101000000 $
b01010111000001010100100000110011 %
b00 &
b00011000111001111010111001000111 '
b00011000111001111010111001000111 (
1*
#326
#330
0*
#335
b11011010110001110001101010110110 #
b11101101110000011110001011010111 $
b01000001011101001110010100111010 %
b11 &
b11011010110001110001101010110110 '
b11011010110001110001101010110110 (
1*
#336
#340
0*
#345
b01001101010001011111011001010011 #
b11000001000011111011111010000100 $
b00111000011011011110100011110100 %
b00 &
b01001101010001011111011001010011 '
b01001101010001011111011001010011 (
1*
#346
#350
0*
#355
b10010000011001000111101100101000 #
b11010010111111010100001101100111 $
b10001101001111111101100010010101 %
b10010000011001000111101100101000 '
b10010000011001000111101100101000 (
1*
#356
#360
0*
#365
b11010100101110010001101101100100 #
b11011110110111000100000110010101 $
b00010101100110101001011110001010 %
b01 &
b11011110110111000100000110010101 '
b11011110110111000100000110010101 (
1*
#366
#370
0*
#375
b00000100110001100111000001111111 #
b10011011100110000011100101011011 $
b00110000111010101010100011011100 %
b00 &
b00000100110001100111000001111111 '
b00000100110001100111000001111111 (
1*
#376
#380
0*
#385
b11010111010010101101011011000110 #
b00001001000111110000000001000110 $
b00011001000101101111000001111001 %
b11010111010010101101011011000110 '
b11010111010010101101011011000110 (
1*
#386
#390
0*
#395
b11110011100000000100100011010100 #
b01111101000000101100100100110100 $
b00100000110011010111011010111101 %
b11 &
b11110011100000000100100011010100 '
b11110011100000000100100011010100 (
1*
#396
#400
0*
#405
b11000010110111010001001100000010 #
b00011010011111110111100101110001 $
b01111110010000101100111001010011 %
b11000010110111010001001100000010 '
b11000010110111010001001100000010 (
1*
#406
#410
0*
#415
b01011011000010110110010011011110 #
b10011000001010010010100011110000 $
b10001110111000001011000000000100 %
b01011011000010110110010011011110 '
b01011011000010110110010011011110 (
1*
#416
#420
0*
#425
b10010010011000011001010011111000 #
b01001110100010001010110000100011 $
b11010111001110111010101110000000 %
b01 &
b01001110100010001010110000100011 '
b01001110100010001010110000100011 (
1*
#426
#430
0*
#435
b00101110010100111111111101100001 #
b11100010111001001100001001010111 $
b01110111010011001001000011010010 %
b00 &
b00101110010100111111111101100001 '
b00101110010100111111111101100001 (
1*
#436
#440
0*
#445
b00010110000010110111011010111100 #
b11110001110100111011011001111011 $
b11010010011101010001101100110001 %
b10 &
b11010010011101010001101100110001 '
b11010010011101010001101100110001 (
1*
#446
#450
0*
#455
b01001111011100010101101011101101 #
b10111110011010011111100101100100 $
b01000000100010100110001111010100 %
b01 &
b10111110011010011111100101100100 '
b10111110011010011111100101100100 (
1*
#456
#460
0*
#465
b00010110010110101100000100010100 #
b10101101011011001101100011001011 $
b00110101000100000000101011001011 %
b11 &
b00010110010110101100000100010100 '
b00010110010110101100000100010100 (
1*
#466
#470
0*
#475
b11011110101101110011001111101001 #
b00010010000110010000010101001110 $
b11111100000001000111011000100100 %
b10 &
b11111100000001000111011000100100 '
b11111100000001000111011000100100 (
1*
#476
#480
0*
#485
b10101110001001010010110000000111 #
b11011000000010100111010100000000 $
b11010101110100110011000111010110 %
b11 &
b10101110001001010010110000000111 '
b10101110001001010010110000000111 (
1*
#486
#490
0*
#495
b11000100001000000111110100111001 #
b11100010101011101101110011111001 $
b10111010100001101000010011010111 %
b10 &
b10111010100001101000010011010111 '
b10111010100001101000010011010111 (
1*
