rtl/utils/pipeline_reg.sv
module pipeline_reg #(
    parameter int WIDTH
    )(
        input logic clk,
        input logic reset,
        input logic stall,
        input logic flush,
        input logic [WIDTH-1:0] d,
        output logic [WIDTH-1:0] q
    );
    always_ff @(posedge clk or posedge reset) begin
        if (reset)
        q <= '0;
        else if (flush)
        q <= '0;
        else if (stall)
        q <= q;
        else 
        q <= d;
    end
endmodule

tb/block_tests/utils/pipeline_reg_tb.sv
module pipeline_reg_tb;

    parameter WIDTH = 32;

    logic clk;
    logic reset;
    logic stall;
    logic flush;

    logic [WIDTH-1:0] d;
    logic [WIDTH-1:0] q;
    logic [WIDTH-1:0] expected;

    int errors = 0;

    // coverage flags
    bit seen_reset  = 0;
    bit seen_flush  = 0;
    bit seen_stall  = 0;
    bit seen_normal = 0;

    // DUT
    pipeline_reg #(.WIDTH(WIDTH)) dut (
        .clk(clk),
        .reset(reset),
        .stall(stall),
        .flush(flush),
        .d(d),
        .q(q)
    );

    // clock
    always #5 clk <= ~clk;

    initial begin
        clk = 0;

        $dumpfile("sim/block_sim/utils/pipeline_reg.vcd");
        $dumpvars(0, pipeline_reg_tb);

        d = 32'hDEADBEEF;
        expected = '0;

        repeat (60) begin
            @(posedge clk);

            // randomize controls
            reset = bit'($urandom);
            stall = bit'($urandom);
            flush = bit'($urandom);

            // expected behavior
            if (reset) begin
                expected = '0;
                seen_reset = 1;
            end
            else if (flush) begin
                expected = '0;
                seen_flush = 1;
            end
            else if (stall) begin
                expected = expected;
                seen_stall = 1;
            end
            else begin
                expected = d;
                seen_normal = 1;
            end

            #1;

            if (q !== expected) begin
                $display("ERROR: reset=%b stall=%b flush=%b q=%h expected=%h",
                         reset, stall, flush, q, expected);
                errors++;
            end
        end

        $display("Coverage:");
        $display(" reset  seen = %0d", seen_reset);
        $display(" flush  seen = %0d", seen_flush);
        $display(" stall  seen = %0d", seen_stall);
        $display(" normal seen = %0d", seen_normal);

        if (errors == 0)
            $display("PASS: pipeline_reg test successful");
        else
            $display("FAIL: %0d errors detected", errors);

        $finish;
    end

endmodule

sim/block_sim/utils/pipeline_reg.vcd
$version Generated by VerilatedVcd $end
$timescale 1ps $end
 $scope module TOP $end
  $scope module pipeline_reg_tb $end
   $var wire 32 / WIDTH [31:0] $end
   $var wire 1 - clk $end
   $var wire 1 # reset $end
   $var wire 1 $ stall $end
   $var wire 1 % flush $end
   $var wire 32 & d [31:0] $end
   $var wire 32 . q [31:0] $end
   $var wire 32 ' expected [31:0] $end
   $var wire 32 ( errors [31:0] $end
   $var wire 1 ) seen_reset $end
   $var wire 1 * seen_flush $end
   $var wire 1 + seen_stall $end
   $var wire 1 , seen_normal $end
   $scope module dut $end
    $var wire 32 0 WIDTH [31:0] $end
    $var wire 1 - clk $end
    $var wire 1 # reset $end
    $var wire 1 $ stall $end
    $var wire 1 % flush $end
    $var wire 32 & d [31:0] $end
    $var wire 32 . q [31:0] $end
   $upscope $end
  $upscope $end
 $upscope $end
$enddefinitions $end


#0
0#
0$
0%
b11011110101011011011111011101111 &
b00000000000000000000000000000000 '
b00000000000000000000000000000000 (
0)
0*
0+
0,
0-
b00000000000000000000000000000000 .
b00000000000000000000000000100000 /
b00000000000000000000000000100000 0
#5
b11011110101011011011111011101111 '
1,
1-
b11011110101011011011111011101111 .
#6
#10
0-
#15
1-
#16
#20
0-
#25
1%
b00000000000000000000000000000000 '
1*
1-
b00000000000000000000000000000000 .
#26
#30
0-
#35
1#
1$
1)
1-
#36
#40
0-
#45
0$
0%
1-
#46
#50
0-
#55
1-
#56
#60
0-
#65
1%
1-
#66
#70
0-
#75
0#
0%
b11011110101011011011111011101111 '
1-
b11011110101011011011111011101111 .
#76
#80
0-
#85
1-
#86
#90
0-
#95
1-
#96
#100
0-
#105
1#
1%
b00000000000000000000000000000000 '
1-
b00000000000000000000000000000000 .
#106
#110
0-
#115
0#
1-
#116
#120
0-
#125
1#
1-
#126
#130
0-
#135
0#
1$
1-
#136
#140
0-
#145
0%
1+
1-
#146
#150
0-
#155
1%
1-
#156
#160
0-
#165
0$
0%
b11011110101011011011111011101111 '
1-
b11011110101011011011111011101111 .
#166
#170
0-
#175
1#
1$
1%
b00000000000000000000000000000000 '
1-
b00000000000000000000000000000000 .
#176
#180
0-
#185
0$
1-
#186
#190
0-
#195
1$
0%
1-
#196
#200
0-
#205
1%
1-
#206
#210
0-
#215
0#
1-
#216
#220
0-
#225
1-
#226
#230
0-
#235
1#
0%
1-
#236
#240
0-
#245
0#
0$
b11011110101011011011111011101111 '
1-
b11011110101011011011111011101111 .
#246
#250
0-
#255
1$
1%
b00000000000000000000000000000000 '
1-
b00000000000000000000000000000000 .
#256
#260
0-
#265
1#
1-
#266
#270
0-
#275
0#
1-
#276
#280
0-
#285
1#
0%
1-
#286
#290
0-
#295
1%
1-
#296
#300
0-
#305
0%
1-
#306
#310
0-
#315
0$
1%
1-
#316
#320
0-
#325
1$
0%
1-
#326
#330
0-
#335
0#
1-
#336
#340
0-
#345
1-
#346
#350
0-
#355
1%
1-
#356
#360
0-
#365
1#
1-
#366
#370
0-
#375
0%
1-
#376
#380
0-
#385
0#
0$
b11011110101011011011111011101111 '
1-
b11011110101011011011111011101111 .
#386
#390
0-
#395
1#
b00000000000000000000000000000000 '
1-
b00000000000000000000000000000000 .
#396
#400
0-
#405
0#
1$
1-
#406
#410
0-
#415
1#
0$
1-
#416
#420
0-
#425
1$
1%
1-
#426
#430
0-
#435
0#
0%
1-
#436
#440
0-
#445
1-
#446
#450
0-
#455
1#
1-
#456
#460
0-
#465
0#
0$
b11011110101011011011111011101111 '
1-
b11011110101011011011111011101111 .
#466
#470
0-
#475
1#
1$
b00000000000000000000000000000000 '
1-
b00000000000000000000000000000000 .
#476
#480
0-
#485
0#
1-
#486
#490
0-
#495
1#
1%
1-
#496
#500
0-
#505
0#
0$
0%
b11011110101011011011111011101111 '
1-
b11011110101011011011111011101111 .
#506
#510
0-
#515
1$
1-
#516
#520
0-
#525
0$
1%
b00000000000000000000000000000000 '
1-
b00000000000000000000000000000000 .
#526
#530
0-
#535
1#
1-
#536
#540
0-
#545
1$
0%
1-
#546
#550
0-
#555
0#
0$
1%
1-
#556
#560
0-
#565
1$
0%
1-
#566
#570
0-
#575
1#
1%
1-
#576
#580
0-
#585
0#
0$
0%
b11011110101011011011111011101111 '
1-
b11011110101011011011111011101111 .
#586
#590
0-
#595
1#
1$
b00000000000000000000000000000000 '
1-
b00000000000000000000000000000000 .
