rtl/pipeline/if_id_reg.sv
module if_id_reg (
    input  logic        clk,
    input  logic        reset,
    input  logic        stall,
    input  logic        flush,

    input  logic [31:0] instruction_in,
    input  logic [31:0] pc_in,
    input  logic [31:0] pc_plus4_in,

    output logic [31:0] instruction,
    output logic [31:0] pc,
    output logic [31:0] pc_plus4
);

    always_ff @(posedge clk or posedge reset) begin
        if (reset)
            {instruction, pc, pc_plus4} <= '0;
        else if (flush)
            {instruction, pc, pc_plus4} <= '0;
        else if (stall)
            {instruction, pc, pc_plus4} <= {instruction, pc, pc_plus4};
        else
            {instruction, pc, pc_plus4} <= {instruction_in, pc_in, pc_plus4_in};
    end

endmodule

tb/block_tests/pipeline/if_id_reg_tb.sv
module if_id_reg_tb;

    logic clk;
    logic reset;
    logic stall;
    logic flush;

    logic [31:0] instruction_in;
    logic [31:0] pc_in;
    logic [31:0] pc_plus4_in;

    logic [31:0] instruction;
    logic [31:0] pc;
    logic [31:0] pc_plus4;

    int errors;

    if_id_reg dut (
        .clk(clk), .reset(reset), .stall(stall), .flush(flush),
        .instruction_in(instruction_in), .pc_in(pc_in), .pc_plus4_in(pc_plus4_in),
        .instruction(instruction), .pc(pc), .pc_plus4(pc_plus4)
    );

    always #5 clk <= ~clk;

    initial begin
        $dumpfile("sim/block_sim/pipeline/if_id_reg.vcd");
        $dumpvars(0, if_id_reg_tb);

        clk = 0; reset = 0; stall = 0; flush = 0;
        instruction_in = 0; pc_in = 0; pc_plus4_in = 0;
        errors = 0;

        #10; reset = 1; #10; reset = 0;

        instruction_in = 32'h12345678; pc_in = 32'h00000100; pc_plus4_in = 32'h00000104;
        #10;

        if (instruction !== 32'h12345678 || pc !== 32'h00000100 || pc_plus4 !== 32'h00000104) begin
            $display("ERROR: Normal pass failed");
            errors++;
        end

        flush = 1; #10;
        if (instruction !== 32'h0 || pc !== 32'h0 || pc_plus4 !== 32'h0) begin
            $display("ERROR: Flush failed");
            errors++;
        end

        instruction_in = 32'hAABBCCDD; pc_in = 32'h00000200; pc_plus4_in = 32'h00000204;
        flush = 0; stall = 1; #10;
        if (instruction !== 32'hAABBCCDD || pc !== 32'h00000200) begin
            $display("ERROR: Stall hold failed");
            errors++;
        end

        instruction_in = 32'h11111111; pc_in = 32'h00000300; pc_plus4_in = 32'h00000304;
        stall = 0; #10;
        if (instruction !== 32'h11111111 || pc !== 32'h00000300) begin
            $display("ERROR: Normal after stall failed");
            errors++;
        end

        if (errors == 0)
            $display("PASS");
        else
            $display("FAIL: %0d errors", errors);

        $finish;
    end

endmodule

sim/block_sim/pipeline/if_id_reg.vcd
$version Generated by VerilatedVcd $end
$timescale 1ps $end
 $scope module TOP $end
  $scope module if_id_reg_tb $end
   $var wire 1 - clk $end
   $var wire 1 # reset $end
   $var wire 1 $ stall $end
   $var wire 1 % flush $end
   $var wire 32 & instruction_in [31:0] $end
   $var wire 32 ' pc_in [31:0] $end
   $var wire 32 ( pc_plus4_in [31:0] $end
   $var wire 32 * instruction [31:0] $end
   $var wire 32 + pc [31:0] $end
   $var wire 32 , pc_plus4 [31:0] $end
   $var wire 32 ) errors [31:0] $end
   $scope module dut $end
    $var wire 1 - clk $end
    $var wire 1 # reset $end
    $var wire 1 $ stall $end
    $var wire 1 % flush $end
    $var wire 32 & instruction_in [31:0] $end
    $var wire 32 ' pc_in [31:0] $end
    $var wire 32 ( pc_plus4_in [31:0] $end
    $var wire 32 * instruction [31:0] $end
    $var wire 32 + pc [31:0] $end
    $var wire 32 , pc_plus4 [31:0] $end
   $upscope $end
  $upscope $end
 $upscope $end
$enddefinitions $end


#0
0#
0$
0%
b00000000000000000000000000000000 &
b00000000000000000000000000000000 '
b00000000000000000000000000000000 (
b00000000000000000000000000000000 )
b00000000000000000000000000000000 *
b00000000000000000000000000000000 +
b00000000000000000000000000000000 ,
0-
#5
1-
#10
1#
0-
#15
1-
#20
0#
b00010010001101000101011001111000 &
b00000000000000000000000100000000 '
b00000000000000000000000100000100 (
0-
#25
b00010010001101000101011001111000 *
b00000000000000000000000100000000 +
b00000000000000000000000100000100 ,
1-
#30
1%
0-
#35
b00000000000000000000000000000000 *
b00000000000000000000000000000000 +
b00000000000000000000000000000000 ,
1-
#40
1$
0%
b10101010101110111100110011011101 &
b00000000000000000000001000000000 '
b00000000000000000000001000000100 (
0-
#45
1-
#50
0$
b00010001000100010001000100010001 &
b00000000000000000000001100000000 '
b00000000000000000000001100000100 (
b00000000000000000000000000000001 )
0-
#55
b00010001000100010001000100010001 *
b00000000000000000000001100000000 +
b00000000000000000000001100000100 ,
1-
